fgvclib/__init__.py
fgvclib-1.0.dist-info/LICENSE
fgvclib-1.0.dist-info/METADATA
fgvclib-1.0.dist-info/WHEEL
fgvclib-1.0.dist-info/top_level.txt
fgvclib-1.0.dist-info/RECORD
