Metadata-Version: 2.1
Name: fgvclib
Version: 1.0
Summary: 一个非常NB的包
Home-page: UNKNOWN
Author: pris-cv
Author-email: changdongliang@bupt.edu.cn
License: UNKNOWN
Platform: UNKNOWN
Classifier: Programming Language :: Python :: 3
Classifier: License :: OSI Approved :: MIT License
Classifier: Operating System :: OS Independent
Requires-Python: >=3
Requires-Dist: pillow
